tea_console/__init__.py
tea_console/config.py
tea_console/console.py
tea_console/enums.py
tea_console/errors.py
tea_console/table.py
tea_console/version.py
tea_console/commands/__init__.py
tea_console/commands/config.py
tea_console/engine/__init__.py
tea_console/engine/config_engine.py
tea_console-0.0.7.dist-info/AUTHORS
tea_console-0.0.7.dist-info/LICENSE
tea_console-0.0.7.dist-info/METADATA
tea_console-0.0.7.dist-info/WHEEL
tea_console-0.0.7.dist-info/top_level.txt
tea_console-0.0.7.dist-info/RECORD
